geomet/.namespace
geomet/screen/__init__.py
geomet/screen/py.typed
geomet/screen/visualization.py
geomet/screen/database/__init__.py
geomet/screen/database/connection.py
geomet/screen/database/loader.py
geomet/screen/models/__init__.py
geomet/screen/models/deck.py
geomet/screen/models/panel.py
geomet/screen/models/panel_layout.py
geomet/screen/models/screen.py
geomet/screen/models/screen_set.py
geomet/screen/render/__init__.py
geomet/screen/render/deck_renderer.py
geomet/screen/render/panel_colors.py
geomet/screen/render/panel_renderer.py
geomet/screen/render/screen_renderer.py
geomet/screen/utils/__init__.py
geomet/screen/utils/mpl_tools.py
geomet_screen-0.1.2.dist-info/METADATA
geomet_screen-0.1.2.dist-info/WHEEL
geomet_screen-0.1.2.dist-info/licenses/LICENSE
geomet_screen-0.1.2.dist-info/RECORD
